Workbook

Sheet Revenue Build
B2: Revenue Build — Capacity-Driven Growth
B4: Line Item | C4: FY26A | D4: FY27E | E4: FY28E | F4: FY29E | G4: FY30E | H4: FY31E
B5: Installed capacity, year-end (GW) | C5: 13.45 | D5: =E13 -> 16.45 | E5: =F13 -> 19.45 | F5: =G13 -> 24.7 | G5: =H13 -> 30 | H5: =I13 -> 32
B6: Average capacity during year (GW) | C6: 12.16 | D6: =(C5+D5)/2 -> 14.95 | E6: =(D5+E5)/2 -> 17.95 | F6: =(E5+F5)/2 -> 22.075 | G6: =(F5+G5)/2 -> 27.35 | H6: =(G5+H5)/2 -> 31
B7: Capacity growth rate (= revenue growth) | C7: n/a | D7: =D6/C6-1 -> 0.22944079 | E7: =E6/D6-1 -> 0.2006689 | F7: =F6/E6-1 -> 0.22980501 | G7: =G6/F6-1 -> 0.2389581 | H7: =H6/G6-1 -> 0.13345521
B8: Revenue (₹ Cr) | C8: 18901 | D8: =C8*(1+D7) -> 23237.66 | E8: =D8*(1+E7) -> 27900.736 | F8: =E8*(1+F7) -> 34312.465 | G8: =F8*(1+G7) -> 42511.706 | H8: =G8*(1+H7) -> 48185.115
B12: Year | C12: FY25 | D12: FY26 | E12: FY27E | F12: FY28E | G12: FY29E | H12: FY30E | I12: FY31E
B13: Capacity (GW) | C13: 10.875 | D13: 13.45 | E13: 16.45 | F13: 19.45 | G13: 24.7 | H13: 30 | I13: 32
B14: Basis | C14: Actual | D14: Actual | E14: +3 GW guided | F14: +3 GW ("similar pace") | G14: Bridge | H14: Target | I14: Steady-state

Sheet Capex Projection
B2: JSW Energy — Capex Projection, FY2027E - FY2031E
B4: Capex Pool
B5: Total Disclosed Program Capex, FY26-FY30 (₹ Cr) | C5: 130000
B6: Less: FY26 Actual Capex Already Spent (₹ Cr) | C6: 18523
B7: Remaining Capex Required, FY27E-FY30E (₹ Cr) | C7: =C5-C6 -> 111477
B9: FY27E Capex confirmed by Management
B10: FY27E Capex (₹ Cr) | C10: 20000
B11: Remaining Capex for FY28E-FY30E (₹ Cr) | C11: =C7-C10 -> 91477
B13: Allocating FY28E - FY30E by Share of Capacity Added
C14: FY28E | D14: FY29E | E14: FY30E
B15: Capacity Added That Year (GW) | C15: ='Revenue Build'!F13-'Revenue Build'!E13 -> 3 | D15: ='Revenue Build'!G13-'Revenue Build'!F13 -> 5.25 | E15: ='Revenue Build'!H13-'Revenue Build'!G13 -> 5.3
B16: Share of FY28E-FY30E Total Capacity Added | C16: =C15/SUM($C$15:$E$15) -> 0.22140221 | D16: =D15/SUM($C$15:$E$15) -> 0.38745387 | E16: =E15/SUM($C$15:$E$15) -> 0.39114391
B17: Allocated Capex (₹ Cr) | C17: =C16*$C$11 -> 20253.21 | D17: =D16*$C$11 -> 35443.118 | E17: =E16*$C$11 -> 35780.672
B19: FY31E (Beyond the Disclosed Program)
B20: Total FY27E-FY30E Capex (₹ Cr) | C20: =C10+SUM(C17:E17) -> 111477
B21: Total FY27E-FY30E Capacity Added (GW) | C21: ='[1]Capacity Build'!C5+SUM('[1]Capacity Build'!D5:F5) -> 16.55
B22: Implied Capex per GW (₹ Cr/GW) | C22: =C20/C21 -> 6735.7704
B23: FY31E Capacity Added (GW) | C23: ='[1]Capacity Build'!G5 -> 2
B24: FY31E Capex (₹ Cr) | C24: =C22*C23 -> 13471.541
B26: FINAL CAPEX SCHEDULE
C27: FY27E | D27: FY28E | E27: FY29E | F27: FY30E | G27: FY31E
B28: Capex (₹ Cr) | C28: =C10 -> 20000 | D28: =C17 -> 20253.21 | E28: =D17 -> 35443.118 | F28: =E17 -> 35780.672 | G28: =C24 -> 13471.541

Sheet Depreciation Schedule
B2: Capex & Depreciation Schedule
B4: Line Item | D4: FY27E | E4: FY28E | F4: FY29E | G4: FY30E | H4: FY31E | J4: Note
B5: Depreciation rate (% of opening asset base) | D5: 0.05 | E5: 0.05 | F5: 0.05 | G5: 0.05 | H5: 0.05 | J5: FY26 actual Depreciation (₹3,185 Cr) ÷ FY25 closing Net PP&E + CWIP (₹64,436 Cr) ≈ 4.9%, rounded to 5%, held flat.
B6: Capex (₹ Cr) | D6: ='Capex Projection'!C28 -> 20000 | E6: ='Capex Projection'!D28 -> 20253.21 | F6: ='Capex Projection'!E28 -> 35443.118 | G6: ='Capex Projection'!F28 -> 35780.672 | H6: ='Capex Projection'!G28 -> 13471.541
B7: Opening net asset base (PP&E + CWIP) | D7: 91988 | E7: =D9 -> 107388.6 | F7: =E9 -> 122272.38 | G7: =F9 -> 151601.88 | H7: =G9 -> 179802.46
B8: Depreciation (₹ Cr) | D8: =D7*D5 -> 4599.4 | E8: =E7*E5 -> 5369.43 | F8: =F7*F5 -> 6113.619 | G8: =G7*G5 -> 7580.094 | H8: =H7*H5 -> 8990.1229
B9: Closing net asset base | D9: =D7+D6-D8 -> 107388.6 | E9: =E7+E6-E8 -> 122272.38 | F9: =F7+F6-F8 -> 151601.88 | G9: =G7+G6-G8 -> 179802.46 | H9: =H7+H6-H8 -> 184283.87

Sheet Price Data
A1: JSW Energy vs. NIFTY 50 — Daily Closing Prices (1-Year, 06-Sep-2025 to 04-Sep-2026)
A4: Date | B4: JSW Energy Close (₹) | C4: NIFTY 50 Close
A5: 45908 | B5: 510.2 | C5: 24773.15
A6: 45909 | B6: 506.1 | C6: 24868.6
A7: 45910 | B7: 519 | C7: 24973.1
A8: 45911 | B8: 521.55 | C8: 25005.5
A9: 45912 | B9: 525.75 | C9: 25114
A10: 45915 | B10: 532 | C10: 25069.2
A11: 45916 | B11: 540.05 | C11: 25239.1
A12: 45917 | B12: 535 | C12: 25330.25
A13: 45918 | B13: 537.8 | C13: 25423.6
A14: 45919 | B14: 545.5 | C14: 25327.05
A15: 45922 | B15: 542.95 | C15: 25202.35
A16: 45923 | B16: 543.85 | C16: 25169.5
... A251: 46269 | B251: 539.85 | C251: 23897.7

Sheet Returns & Deviations
A1: Daily Returns and Deviations from Mean
A6: Date | B6: JSW Return | C6: NIFTY Return | D6: JSW Deviation (Return - Mean) | E6: NIFTY Deviation (Return - Mean) | F6: Cross Product (JSW Dev x NIFTY Dev) | G6: NIFTY Deviation²
A7: 45909 | B7: =('Price Data'!B6-'Price Data'!B5)/'Price Data'!B5 -> -0.0080360643 | C7: =('Price Data'!C6-'Price Data'!C5)/'Price Data'!C5 -> 0.0038529618 | D7: =B7-$B$4 -> -0.0080360643 | E7: =C7-$C$5 -> 0.0038529618 | F7: =D7*E7 -> -3.0962649e-05 | G7: =E7^2 -> 1.4845314e-05
A8: 45910 | B8: =('Price Data'!B7-'Price Data'!B6)/'Price Data'!B6 -> 0.025489034 | C8: =('Price Data'!C7-'Price Data'!C6)/'Price Data'!C6 -> 0.0042020862 | D8: =B8-$B$4 -> 0.025489034 | E8: =C8-$C$5 -> 0.0042020862 | F8: =D8*E8 -> 0.00010710712 | G8: =E8^2 -> 1.7657528e-05
A9: 45911 | B9: =('Price Data'!B8-'Price Data'!B7)/'Price Data'!B7 -> 0.0049132948 | C9: =('Price Data'!C8-'Price Data'!C7)/'Price Data'!C7 -> 0.001297396 | D9: =B9-$B$4 -> 0.0049132948 | E9: =C9-$C$5 -> 0.001297396 | F9: =D9*E9 -> 6.374489e-06 | G9: =E9^2 -> 1.6832364e-06
A10: 45912 | B10: =('Price Data'!B9-'Price Data'!B8)/'Price Data'!B8 -> 0.0080529192 | C10: =('Price Data'!C9-'Price Data'!C8)/'Price Data'!C8 -> 0.0043390454 | D10: =B10-$B$4 -> 0.0080529192 | E10: =C10-$C$5 -> 0.0043390454 | F10: =D10*E10 -> 3.4941982e-05 | G10: =E10^2 -> 1.8827315e-05
A11: 45915 | B11: =('Price Data'!B10-'Price Data'!B9)/'Price Data'!B9 -> 0.011887779 | C11: =('Price Data'!C10-'Price Data'!C9)/'Price Data'!C9 -> -0.0017838656 | D11: =B11-$B$4 -> 0.011887779 | E11: =C11-$C$5 -> -0.0017838656 | F11: =D11*E11 -> -2.12062e-05 | G11: =E11^2 -> 3.1821764e-06
A12: 45916 | B12: =('Price Data'!B11-'Price Data'!B10)/'Price Data'!B10 -> 0.015131579 | C12: =('Price Data'!C11-'Price Data'!C10)/'Price Data'!C10 -> 0.0067772406 | D12: =B12-$B$4 -> 0.015131579 | E12: =C12-$C$5 -> 0.0067772406 | F12: =D12*E12 -> 0.00010255035 | G12: =E12^2 -> 4.593099e-05
A13: 45917 | B13: =('Price Data'!B12-'Price Data'!B11)/'Price Data'!B11 -> -0.009350986 | C13: =('Price Data'!C12-'Price Data'!C11)/'Price Data'!C11 -> 0.00361146 | D13: =B13-$B$4 -> -0.009350986 | E13: =C13-$C$5 -> 0.00361146 | F13: =D13*E13 -> -3.3770712e-05 | G13: =E13^2 -> 1.3042643e-05
A14: 45918 | B14: =('Price Data'!B13-'Price Data'!B12)/'Price Data'!B12 -> 0.0052336449 | C14: =('Price Data'!C13-'Price Data'!C12)/'Price Data'!C12 -> 0.003685317 | D14: =B14-$B$4 -> 0.0052336449 | E14: =C14-$C$5 -> 0.003685317 | F14: =D14*E14 -> 1.928764e-05 | G14: =E14^2 -> 1.3581561e-05
A15: 45919 | B15: =('Price Data'!B14-'Price Data'!B13)/'Price Data'!B13 -> 0.01431759 | C15: =('Price Data'!C14-'Price Data'!C13)/'Price Data'!C13 -> -0.0037976526 | D15: =B15-$B$4 -> 0.01431759 | E15: =C15-$C$5 -> -0.0037976526 | F15: =D15*E15 -> -5.4373233e-05 | G15: =E15^2 -> 1.4422165e-05
A16: 45922 | B16: =('Price Data'!B15-'Price Data'!B14)/'Price Data'!B14 -> -0.0046746104 | C16: =('Price Data'!C15-'Price Data'!C14)/'Price Data'!C14 -> -0.0049235896 | D16: =B16-$B$4 -> -0.0046746104 | E16: =C16-$C$5 -> -0.0049235896 | F16: =D16*E16 -> 2.3015863e-05 | G16: =E16^2 -> 2.4241735e-05
A17: 45923 | B17: =('Price Data'!B16-'Price Data'!B15)/'Price Data'!B15 -> 0.0016576112 | C17: =('Price Data'!C16-'Price Data'!C15)/'Price Data'!C15 -> -0.0013034499 | D17: =B17-$B$4 -> 0.0016576112 | E17: =C17-$C$5 -> -0.0013034499 | F17: =D17*E17 -> -2.1606131e-06 | G17: =E17^2 -> 1.6989816e-06
A18: 45924 | B18: =('Price Data'!B17-'Price Data'!B16)/'Price Data'!B16 -> -0.015997058 | C18: =('Price Data'!C17-'Price Data'!C16)/'Price Data'!C16 -> -0.0044736685 | D18: =B18-$B$4 -> -0.015997058 | E18: =C18-$C$5 -> -0.0044736685 | F18: =D18*E18 -> 7.1565535e-05 | G18: =E18^2 -> 2.001371e-05
... A252: 46269 | B252: =('Price Data'!B251-'Price Data'!B250)/'Price Data'!B250 -> 0.00064874884 | C252: =('Price Data'!C251-'Price Data'!C250)/'Price Data'!C250 -> 0.0010157728 | D252: =B252-$B$4 -> 0.00064874884 | E252: =C252-$C$5 -> 0.0010157728 | F252: =D252*E252 -> 6.589814e-07 | G252: =E252^2 -> 1.0317943e-06

Sheet Beta Calculation
A1: JSW Energy — Manual Beta Calculation (Covariance / Variance Method)
B3: Beta Calculation
B4: Covariance JSW & NIFTY50 | C4: =COVAR('Returns & Deviations'!B7:B252,'Returns & Deviations'!C7:C252) -> 6.2822832e-05
B5: Variance of Market (NIFTY 50) | C5: =VARP('Returns & Deviations'!C7:C252) -> 6.9735798e-05
B6: BETA (COVAR / VARP) | C6: =C4/C5 -> 0.9008692

Sheet WACC Build
B2: WACC
B4: Input | C4: Calculation
B5: Risk-free rate (Rf) | C5: 0.068
B6: Equity Beta (β) | C6: 0.9
B7: Equity Risk Premium (ERP) | C7: 0.065
B8: Cost of Equity (Ke) = Rf + β×ERP | C8: =C5+C6*C7 -> 0.1265
B10: Cost of debt, pre-tax (Kd) | C10: 0.083
B11: Tax rate (for debt tax shield) | C11: 0.25
B12: Cost of debt, post-tax = Kd×(1−t) | C12: =C10*(1-C11) -> 0.06225
B14: Weight — Equity (E/V) | C14: 0.5
B15: Weight — Debt (D/V) | C15: =1-C14 -> 0.5
B17: WACC = We×Ke + Wd×Kd(post-tax) | C17: =C14*C8+C15*C12 -> 0.094375

Sheet FCFF Projection
B2: JSW Energy — FCFF Projection, FY27E–FY31E (₹ Crore)
B4: Line Item | D4: FY27E | E4: FY28E | F4: FY29E | G4: FY30E | H4: FY31E | J4: Note
B5: Revenue | D5: ='Revenue Build'!D8 -> 23237.66 | E5: ='Revenue Build'!E8 -> 27900.736 | F5: ='Revenue Build'!F8 -> 34312.465 | G5: ='Revenue Build'!G8 -> 42511.706 | H5: ='Revenue Build'!H8 -> 48185.115
B6: Revenue growth % | D6: ='Revenue Build'!D7 -> 0.22944079 | E6: ='Revenue Build'!E7 -> 0.2006689 | F6: ='Revenue Build'!F7 -> 0.22980501 | G6: ='Revenue Build'!G7 -> 0.2389581 | H6: ='Revenue Build'!H7 -> 0.13345521
B7: EBITDA margin (%) | D7: 0.48 | E7: 0.48 | F7: 0.48 | G7: 0.48 | H7: 0.48
B8: EBITDA | D8: =D5*D7 -> 11154.077 | E8: =E5*E7 -> 13392.353 | F8: =F5*F7 -> 16469.983 | G8: =G5*G7 -> 20405.619 | H8: =H5*H7 -> 23128.855
B9: Less: Depreciation | D9: ='Depreciation Schedule'!D8 -> 4599.4 | E9: ='Depreciation Schedule'!E8 -> 5369.43 | F9: ='Depreciation Schedule'!F8 -> 6113.619 | G9: ='Depreciation Schedule'!G8 -> 7580.094 | H9: ='Depreciation Schedule'!H8 -> 8990.1229
B10: EBIT | D10: =D8-D9 -> 6554.677 | E10: =E8-E9 -> 8022.9233 | F10: =F8-F9 -> 10356.364 | G10: =G8-G9 -> 12825.525 | H10: =H8-H9 -> 14138.732
B11: Tax rate (%) | D11: 0.25 | E11: 0.25 | F11: 0.25 | G11: 0.25 | H11: 0.25
B12: Less: Tax on EBIT | D12: =D10*D11 -> 1638.6692 | E12: =E10*E11 -> 2005.7308 | F12: =F10*F11 -> 2589.0911 | G12: =G10*G11 -> 3206.3813 | H12: =H10*H11 -> 3534.6831
B13: NOPAT (EBIT x (1 − tax rate)) | D13: =D10-D12 -> 4916.0077 | E13: =E10-E12 -> 6017.1925 | F13: =F10-F12 -> 7767.2732 | G13: =G10-G12 -> 9619.1438 | H13: =H10-H12 -> 10604.049
B14: Add: Depreciation | D14: =D9 -> 4599.4 | E14: =E9 -> 5369.43 | F14: =F9 -> 6113.619 | G14: =G9 -> 7580.094 | H14: =H9 -> 8990.1229
B15: Less: Capex | D15: ='Depreciation Schedule'!D6 -> 20000 | E15: ='Depreciation Schedule'!E6 -> 20253.21 | F15: ='Depreciation Schedule'!F6 -> 35443.118 | G15: ='Depreciation Schedule'!G6 -> 35780.672 | H15: ='Depreciation Schedule'!H6 -> 13471.541
B16: Debtor days (Screener) | D16: 31 | E16: 31 | F16: 31 | G16: 31 | H16: 31
B17: Incremental revenue (this yr − prior yr) | D17: =D5-'Revenue Build'!C8 -> 4336.6604 | E17: =E5-D5 -> 4663.0757 | F17: =F5-E5 -> 6411.729 | G17: =G5-F5 -> 8199.2414 | H17: =H5-G5 -> 5673.4087
B18: Less: Increase in working capital (ΔWC) | D18: =D17*D16/365 -> 368.3191 | E18: =E17*E16/365 -> 396.04204 | F18: =F17*F16/365 -> 544.55781 | G18: =G17*G16/365 -> 696.37392 | H18: =H17*H16/365 -> 481.85115 | J18: Formula: Incremental revenue x (Debtor Days / 365)
B20: FCFF = NOPAT + Depreciation − Capex − ΔWC | D20: =D13+D14-D15-D18 -> -10852.911 | E20: =E13+E14-E15-E18 -> -9262.6299 | F20: =F13+F14-F15-F18 -> -22106.784 | G20: =G13+G14-G15-G18 -> -19277.808 | H20: =H13+H14-H15-H18 -> 5640.7802

Sheet DCF Valuation
B2: DCF Valuation — Intrinsic Value per Share
B4: Selected WACC | C4: ='WACC Build'!C17 -> 0.094375
B5: Selected Terminal Growth (g) | C5: 0.065
B7: Line Item | C7: FY27E | D7: FY28E | E7: FY29E | F7: FY30E | G7: FY31E
B8: FCFF (₹ Cr) | C8: ='FCFF Projection'!D20 -> -10852.911 | D8: ='FCFF Projection'!E20 -> -9262.6299 | E8: ='FCFF Projection'!F20 -> -22106.784 | F8: ='FCFF Projection'!G20 -> -19277.808 | G8: ='FCFF Projection'!H20 -> 5640.7802
B9: Discount factor | C9: =1/(1+$C$4)^1 -> 0.91376356 | D9: =1/(1+$C$4)^2 -> 0.83496385 | E9: =1/(1+$C$4)^3 -> 0.76295954 | F9: =1/(1+$C$4)^4 -> 0.69716463 | G9: =1/(1+$C$4)^5 -> 0.63704364
B10: PV of FCFF | C10: =C8*C9 -> -9916.995 | D10: =D8*D9 -> -7733.9611 | E10: =E8*E9 -> -16866.582 | F10: =F8*F9 -> -13439.806 | G10: =G8*G9 -> 3593.4232
B12: Sum PV of FCFF (FY27-31) | C12: =SUM(C10:G10) -> -44363.92
B13: Terminal Value (= FY31E FCFF x (1+g) / (WACC-g)) | C13: =G8*(1+$C$5)/($C$4-$C$5) -> 204508.29
B14: PV of Terminal Value | C14: =C13*G9 -> 130280.7
B15: Enterprise Value | C15: =C12+C14 -> 85916.783
B16: Less: Net Debt (FY26) | C16: 65567
B17: Equity Value | C17: =C15-C16 -> 20349.783
B18: ÷ Shares Outstanding (Cr) | C18: 175.6
B20: Intrinsic Value / Share | C20: =C17/C18 -> 115.88715
